[
{"name":"scriptSources","cat":"job","ph":"X","ts":1720738766125000,"dur":27000,"pid":1,"tid":0,"args":[]},
{"name":"parseBuildFiles","cat":"job","ph":"X","ts":1720738766157000,"dur":4000,"pid":1,"tid":0,"args":["cached"]},
{"name":"cliImports","cat":"job","ph":"X","ts":1720738766162000,"dur":3000,"pid":1,"tid":0,"args":[]},
{"name":"runIvyDeps","cat":"job","ph":"X","ts":1720738766165000,"dur":1000,"pid":1,"tid":0,"args":["cached"]},
{"name":"scalaVersion","cat":"job","ph":"X","ts":1720738766166000,"dur":1000,"pid":1,"tid":0,"args":["cached"]},
{"name":"platformSuffix","cat":"job","ph":"X","ts":1720738766167000,"dur":1000,"pid":1,"tid":0,"args":["cached"]},
{"name":"ivyDeps","cat":"job","ph":"X","ts":1720738766168000,"dur":12000,"pid":1,"tid":0,"args":["cached"]},
{"name":"mandatoryIvyDeps.super.mill.scalalib.JavaModule.mandatoryIvyDeps","cat":"job","ph":"X","ts":1720738766180000,"dur":2000,"pid":1,"tid":0,"args":["cached"]},
{"name":"scalaOrganization","cat":"job","ph":"X","ts":1720738766182000,"dur":1000,"pid":1,"tid":0,"args":["cached"]},
{"name":"scalaLibraryIvyDeps","cat":"job","ph":"X","ts":1720738766183000,"dur":2000,"pid":1,"tid":0,"args":["cached"]},
{"name":"mandatoryIvyDeps","cat":"job","ph":"X","ts":1720738766185000,"dur":1000,"pid":1,"tid":0,"args":["cached"]},
{"name":"transitiveIvyDeps","cat":"job","ph":"X","ts":1720738766186000,"dur":1000,"pid":1,"tid":0,"args":["cached"]},
{"name":"resolvedRunIvyDeps","cat":"job","ph":"X","ts":1720738766188000,"dur":10000,"pid":1,"tid":0,"args":["cached"]},
{"name":"transitiveLocalClasspath","cat":"job","ph":"X","ts":1720738766198000,"dur":1000,"pid":1,"tid":0,"args":["cached"]},
{"name":"compileResources","cat":"job","ph":"X","ts":1720738766199000,"dur":3000,"pid":1,"tid":0,"args":[]},
{"name":"enclosingClasspath","cat":"job","ph":"X","ts":1720738766202000,"dur":2000,"pid":1,"tid":0,"args":[]},
{"name":"lineNumberPluginClasspath","cat":"job","ph":"X","ts":1720738766204000,"dur":1000,"pid":1,"tid":0,"args":["cached"]},
{"name":"unmanagedClasspath","cat":"job","ph":"X","ts":1720738766206000,"dur":1000,"pid":1,"tid":0,"args":["cached"]},
{"name":"localCompileClasspath","cat":"job","ph":"X","ts":1720738766207000,"dur":1000,"pid":1,"tid":0,"args":["cached"]},
{"name":"resources.super.mill.scalalib.JavaModule.resources","cat":"job","ph":"X","ts":1720738766208000,"dur":3000,"pid":1,"tid":0,"args":[]},
{"name":"resources","cat":"job","ph":"X","ts":1720738766211000,"dur":1000,"pid":1,"tid":0,"args":["cached"]},
{"name":"mill.scalalib.ZincWorkerModule.classpath","cat":"job","ph":"X","ts":1720738766212000,"dur":2000,"pid":1,"tid":0,"args":["cached"]},
{"name":"mill.scalalib.ZincWorkerModule.zincLogDebug","cat":"job","ph":"X","ts":1720738766214000,"dur":2000,"pid":1,"tid":0,"args":[]},
{"name":"mill.scalalib.ZincWorkerModule.worker","cat":"job","ph":"X","ts":1720738766216000,"dur":73000,"pid":1,"tid":0,"args":[]},
{"name":"upstreamCompileOutput","cat":"job","ph":"X","ts":1720738766289000,"dur":0,"pid":1,"tid":0,"args":["cached"]},
{"name":"sources.super.mill.scalalib.JavaModule.sources","cat":"job","ph":"X","ts":1720738766290000,"dur":3000,"pid":1,"tid":0,"args":[]},
{"name":"sources","cat":"job","ph":"X","ts":1720738766293000,"dur":1000,"pid":1,"tid":0,"args":["cached"]},
{"name":"generateScriptSources","cat":"job","ph":"X","ts":1720738766294000,"dur":1000,"pid":1,"tid":0,"args":["cached"]},
{"name":"generatedSources","cat":"job","ph":"X","ts":1720738766295000,"dur":0,"pid":1,"tid":0,"args":["cached"]},
{"name":"allSources","cat":"job","ph":"X","ts":1720738766295000,"dur":1000,"pid":1,"tid":0,"args":["cached"]},
{"name":"allSourceFiles","cat":"job","ph":"X","ts":1720738766296000,"dur":1000,"pid":1,"tid":0,"args":["cached"]},
{"name":"compileIvyDeps","cat":"job","ph":"X","ts":1720738766297000,"dur":0,"pid":1,"tid":0,"args":["cached"]},
{"name":"transitiveCompileIvyDeps","cat":"job","ph":"X","ts":1720738766297000,"dur":1000,"pid":1,"tid":0,"args":["cached"]},
{"name":"resolvedIvyDeps","cat":"job","ph":"X","ts":1720738766298000,"dur":2000,"pid":1,"tid":0,"args":["cached"]},
{"name":"transitiveCompileClasspath","cat":"job","ph":"X","ts":1720738766300000,"dur":0,"pid":1,"tid":0,"args":["cached"]},
{"name":"compileClasspath","cat":"job","ph":"X","ts":1720738766300000,"dur":2000,"pid":1,"tid":0,"args":["cached"]},
{"name":"javacOptions","cat":"job","ph":"X","ts":1720738766302000,"dur":0,"pid":1,"tid":0,"args":["cached"]},
{"name":"mandatoryScalacOptions","cat":"job","ph":"X","ts":1720738766303000,"dur":0,"pid":1,"tid":0,"args":["cached"]},
{"name":"scalacPluginIvyDeps","cat":"job","ph":"X","ts":1720738766303000,"dur":1000,"pid":1,"tid":0,"args":["cached"]},
{"name":"enablePluginScalacOptions.super.mill.scalalib.ScalaModule.enablePluginScalacOptions","cat":"job","ph":"X","ts":1720738766304000,"dur":2000,"pid":1,"tid":0,"args":["cached"]},
{"name":"scalacOptions.super.mill.scalalib.ScalaModule.scalacOptions","cat":"job","ph":"X","ts":1720738766306000,"dur":1000,"pid":1,"tid":0,"args":["cached"]},
{"name":"scalacOptions","cat":"job","ph":"X","ts":1720738766307000,"dur":1000,"pid":1,"tid":0,"args":["cached"]},
{"name":"allScalacOptions","cat":"job","ph":"X","ts":1720738766308000,"dur":0,"pid":1,"tid":0,"args":["cached"]},
{"name":"scalaCompilerClasspath","cat":"job","ph":"X","ts":1720738766308000,"dur":1000,"pid":1,"tid":0,"args":["cached"]},
{"name":"scalacPluginClasspath.super.mill.scalalib.ScalaModule.scalacPluginClasspath","cat":"job","ph":"X","ts":1720738766310000,"dur":2000,"pid":1,"tid":0,"args":["cached"]},
{"name":"scalacPluginClasspath","cat":"job","ph":"X","ts":1720738766312000,"dur":1000,"pid":1,"tid":0,"args":["cached"]},
{"name":"zincReportCachedProblems","cat":"job","ph":"X","ts":1720738766314000,"dur":1000,"pid":1,"tid":0,"args":[]},
{"name":"compile","cat":"job","ph":"X","ts":1720738766316000,"dur":0,"pid":1,"tid":0,"args":["cached"]},
{"name":"localClasspath","cat":"job","ph":"X","ts":1720738766316000,"dur":1000,"pid":1,"tid":0,"args":["cached"]},
{"name":"runClasspath","cat":"job","ph":"X","ts":1720738766317000,"dur":1000,"pid":1,"tid":0,"args":["cached"]},
{"name":"scriptImportGraph","cat":"job","ph":"X","ts":1720738766318000,"dur":1000,"pid":1,"tid":0,"args":["cached"]},
{"name":"methodCodeHashSignatures","cat":"job","ph":"X","ts":1720738766320000,"dur":8000,"pid":1,"tid":0,"args":["cached"]}
]
